tweetwatcher/__init__.py
tweetwatcher/back.py
tweetwatcher/tweetwatcher.py
tweetwatcher-0.0.3.dist-info/LICENSE
tweetwatcher-0.0.3.dist-info/METADATA
tweetwatcher-0.0.3.dist-info/WHEEL
tweetwatcher-0.0.3.dist-info/entry_points.txt
tweetwatcher-0.0.3.dist-info/top_level.txt
tweetwatcher-0.0.3.dist-info/RECORD
