Metadata-Version: 2.1
Name: tweetwatcher
Version: 0.0.3
Summary: A simple tweet watcher.
Home-page: https://github.com/dhsdshdhk/tweetwatcher
Author: John Doe
Author-email: author@example.com
License: UNKNOWN
Platform: UNKNOWN
Classifier: Programming Language :: Python :: 3
Classifier: License :: OSI Approved :: MIT License
Classifier: Operating System :: OS Independent
Requires-Python: >=3.6
Requires-Dist: pyqt5
Requires-Dist: pandas
Requires-Dist: openpyxl
